MANIFEST.in
README.rst
setup.py
fimgs/__init__.py
fimgs/admin.py
fimgs/api_views.py
fimgs/apps.py
fimgs/forms.py
fimgs/models.py
fimgs/tests.py
fimgs/urls.py
fimgs/views.py
fimgs.egg-info/PKG-INFO
fimgs.egg-info/SOURCES.txt
fimgs.egg-info/dependency_links.txt
fimgs.egg-info/top_level.txt
fimgs/migrations/0001_initial.py
fimgs/migrations/__init__.py